carddeck/__init__.py
carddeck/cards.py
carddeck/deck.py
carddeck/errors.py
carddeck/pokerhands.py
carddeck-0.1.3.dist-info/LICENSE.txt
carddeck-0.1.3.dist-info/METADATA
carddeck-0.1.3.dist-info/WHEEL
carddeck-0.1.3.dist-info/top_level.txt
carddeck-0.1.3.dist-info/RECORD
