Metadata-Version: 2.1
Name: carddeck
Version: 0.1.3
Summary: Python package for a deck of cards
Home-page: https://github.com/mpytel/carddeck.git
Author: Martin Pytel
Author-email: martin@pidev.com
License: MIT
Keywords: card game, sample
Platform: UNKNOWN
Classifier: Development Status :: 3 - Alpha
Classifier: Intended Audience :: Developers
Classifier: Topic :: Software Development
Classifier: License :: OSI Approved :: MIT License
Classifier: Programming Language :: Python
Classifier: Programming Language :: Python :: 3
Classifier: Programming Language :: Python :: 3.6
Classifier: Programming Language :: Python :: 3 :: Only
Requires-Python: >=3.6.0
